{
    "all": 61697,
    "arrow": 61698,
    "ball": 61699,
    "bell": 61700,
    "book": 61701,
    "bookmark-marked": 61702,
    "bookmark": 61703,
    "burger": 61704,
    "business_lunch": 61705,
    "car": 61706,
    "care": 61707,
    "check": 61708,
    "clap": 61709,
    "close": 61710,
    "crown": 61711,
    "date": 61712,
    "district": 61713,
    "egg": 61714,
    "ellipse": 61715,
    "feather": 61716,
    "filter": 61717,
    "food": 61718,
    "fork_spoon": 61719,
    "gps": 61720,
    "health": 61721,
    "home": 61722,
    "lang": 61723,
    "load": 61724,
    "logo": 61725,
    "money_bag": 61726,
    "more": 61727,
    "pet": 61728,
    "photo": 61729,
    "pin": 61730,
    "pizza": 61731,
    "plate": 61732,
    "price": 61733,
    "reply": 61734,
    "search": 61735,
    "share": 61736,
    "shop": 61737,
    "star": 61738,
    "steak": 61739,
    "travel": 61740,
    "user": 61741,
    "zoom": 61742
}